{
	"class" : {
		"activeWindow" : "mt 11/12/2014 11:10:44.146",
		"borderWidth" : "mt 9/25/2012 09:10:25.436",
		"boxExtent" : "mt 12/6/2012 15:07:36.437",
		"closeBoxImage" : "mt 12/5/2012 16:49:39.901",
		"collapseBoxImage" : "mt 12/6/2012 15:04:21.346",
		"expandBoxImage" : "mt 12/6/2012 15:03:59.317",
		"morph:label:" : "mt 5/1/2011 11:22:23.26" },
	"instance" : {
		"aboutRequested" : "mt 5/2/2011 16:12:35.236",
		"activate" : "mt 4/21/2015 11:00",
		"addApplicationBox" : "mt 5/1/2011 12:11:32.293",
		"addCloseBox" : "mt 5/1/2011 12:14:15.052",
		"addCollapseBox" : "mt 12/6/2012 15:11:09.671",
		"addLabelArea" : "mt 5/1/2011 11:38:13.541",
		"addLockBox" : "mt 5/20/2014 10:37:30.079",
		"addSpacer" : "mt 5/1/2011 11:43:36.498",
		"adoptPaneColor:" : "mt 5/3/2016 11:21:56.214",
		"buildWindowMenu" : "mt 5/2/2011 16:14:12.012",
		"closeBoxHit" : "mt 12/4/2012 11:07:27.141",
		"closeRequested" : "mt 12/4/2012 11:07:04.37",
		"createAboutBox" : "mt 5/2/2011 16:10:39.773",
		"createBox:" : "mt 12/6/2012 15:05:07.403",
		"createCloseBox" : "mt 12/5/2012 14:51:27.391",
		"createCollapseBox" : "mt 12/5/2012 14:51:01.675",
		"createExpandBox" : "mt 12/5/2012 14:51:49.051",
		"createLabel" : "mt 9/13/2013 16:45:22.184",
		"createLockBox" : "mt 4/19/2015 11:41",
		"createMenuBox" : "mt 12/5/2012 14:52:18.039",
		"dimWindowButtons" : "mt 12/5/2012 15:05:19.745",
		"initializeLabelArea" : "mt 12/6/2012 15:12:04.292",
		"initializeLabelAreaContents" : "mt 5/20/2014 10:39:05.531",
		"isActive" : "mt 11/12/2014 11:10:06.202",
		"lockWindow" : "mt 8/23/2014 11:20:46.015",
		"paneColor" : "mt 8/24/2016 15:28",
		"paneColorToUseWhenNotActive" : "mt 5/3/2016 11:30:21.824",
		"passivate" : "mt 11/12/2014 11:09:46.695",
		"pushOtherWindowsAside" : "mt 7/24/2014 14:48:19.527",
		"setFramesForLabelArea" : "mt 8/24/2016 15:58",
		"toggleLockWindow" : "mt 5/20/2014 10:44:38.308",
		"undimWindowButtons" : "mt 12/5/2012 15:05:22.301",
		"unlockWindow" : "mt 8/23/2014 11:20:50.042",
		"walkToCenter:" : "mt 5/20/2014 11:13:34.47",
		"yellowButtonActivity:" : "mt 12/11/2012 11:06:37.647" } }
