{
	"class" : {
		 },
	"instance" : {
		"performTest" : "mt 8/1/2019 11:49",
		"setUp" : "mt 7/17/2019 09:18",
		"tearDown" : "mt 7/17/2019 09:18",
		"test01AllResults" : "mt 7/30/2019 10:56",
		"test01ConnectDefault" : "mt 8/1/2019 10:50",
		"test01MatchInputKind" : "mt 7/29/2019 18:43",
		"test01NewInstance" : "mt 8/1/2019 10:44",
		"test02AllResultsForRecursiveScript" : "mt 7/30/2019 10:57",
		"test02ConnectAllResults" : "mt 8/1/2019 10:46",
		"test02MatchGlobal" : "mt 7/29/2019 18:51",
		"test02SimpleScenario" : "mt 7/26/2019 11:32",
		"test03AllResultsForInfinitiveScript" : "mt 7/30/2019 11:05",
		"test03ConnectSelectedResults" : "mt 8/1/2019 10:50",
		"test03KnownScripts" : "mt 7/26/2019 14:07",
		"test03MatchIdentityScript" : "mt 7/30/2019 10:27",
		"test04AddQuery" : "mt 7/25/2019 16:11",
		"test04MultipleProducers" : "mt 8/1/2019 10:58",
		"test04ScriptOrganization" : "mt 7/26/2019 14:26",
		"test04SelectedResults" : "mt 7/30/2019 11:14",
		"test05KeepSelectedResults" : "mt 7/30/2019 11:21",
		"test05MultipleConsumers" : "mt 8/1/2019 11:02",
		"test05ObjectsOnly" : "mt 7/26/2019 14:39",
		"test06ConnectPushObjects" : "mt 8/1/2019 11:04",
		"test06ScriptOnly" : "mt 7/26/2019 14:35",
		"test07ConnectPushTuples" : "mt 8/1/2019 11:06",
		"test07KeepAddedQuery" : "mt 7/25/2019 16:04",
		"test08DisconnectKeepObjects" : "mt 8/1/2019 11:08",
		"test09DisconnectKeepTuples" : "mt 8/1/2019 11:13",
		"test10CycleWithOnePane" : "mt 8/1/2019 11:36",
		"test11ViewUpdate" : "mt 7/25/2019 16:06",
		"test17KeepAppropriateScript" : "mt 7/25/2019 16:15",
		"test18NoDoubleEmpty" : "mt 7/25/2019 16:05",
		"test19SelfLoop" : "mt 7/25/2019 16:06",
		"test20DirectLoop" : "mt 7/25/2019 16:06",
		"test21DirectLoopSelfUpdate" : "mt 7/25/2019 16:07",
		"test22DeferredLoop" : "mt 7/25/2019 16:07",
		"test23PropagateOnNotifier" : "mt 7/25/2019 16:07",
		"test24PropagateOnScriptChange" : "mt 7/25/2019 16:05" } }
